{
  "repos": [
    {
      "name": "torchair",
      "path": "Ascend/torchair",
      "merged": 2297,
      "open": 248,
      "total": 2545
    },
    {
      "name": "ge",
      "path": "cann/ge",
      "merged": 1824,
      "open": 122,
      "total": 1946
    },
    {
      "name": "graph-autofusion",
      "path": "cann/graph-autofusion",
      "merged": 486,
      "open": 68,
      "total": 554
    },
    {
      "name": "hixl",
      "path": "cann/hixl",
      "merged": 531,
      "open": 17,
      "total": 548
    },
    {
      "name": "torchtitan-npu",
      "path": "cann/torchtitan-npu",
      "merged": 274,
      "open": 21,
      "total": 295
    }
  ],
  "unique_authors": 717,
  "generated_at": "2026-06-19"
}