{
  "repos": [
    {
      "name": "torchair",
      "path": "Ascend/torchair",
      "merged": 2299,
      "open": 252,
      "total": 2551
    },
    {
      "name": "ge",
      "path": "cann/ge",
      "merged": 1842,
      "open": 131,
      "total": 1973
    },
    {
      "name": "graph-autofusion",
      "path": "cann/graph-autofusion",
      "merged": 499,
      "open": 67,
      "total": 566
    },
    {
      "name": "hixl",
      "path": "cann/hixl",
      "merged": 533,
      "open": 21,
      "total": 554
    },
    {
      "name": "torchtitan-npu",
      "path": "cann/torchtitan-npu",
      "merged": 278,
      "open": 19,
      "total": 297
    }
  ],
  "unique_authors": 721,
  "generated_at": "2026-06-22"
}