{
  "weeks": [
    "2023-W27",
    "2023-W28",
    "2023-W29",
    "2023-W30",
    "2023-W31",
    "2023-W32",
    "2023-W33",
    "2023-W34",
    "2023-W35",
    "2023-W36",
    "2023-W37",
    "2023-W38",
    "2023-W39",
    "2023-W41",
    "2023-W42",
    "2023-W43",
    "2023-W44",
    "2023-W45",
    "2023-W46",
    "2023-W47",
    "2023-W48",
    "2023-W49",
    "2023-W50",
    "2023-W51",
    "2023-W52",
    "2024-W01",
    "2024-W02",
    "2024-W03",
    "2024-W04",
    "2024-W05",
    "2024-W06",
    "2024-W07",
    "2024-W08",
    "2024-W09",
    "2024-W10",
    "2024-W11",
    "2024-W12",
    "2024-W13",
    "2024-W14",
    "2024-W15",
    "2024-W16",
    "2024-W17",
    "2024-W18",
    "2024-W19",
    "2024-W20",
    "2024-W21",
    "2024-W22",
    "2024-W23",
    "2024-W24",
    "2024-W25",
    "2024-W26",
    "2024-W27",
    "2024-W28",
    "2024-W29",
    "2024-W30",
    "2024-W31",
    "2024-W32",
    "2024-W33",
    "2024-W34",
    "2024-W35",
    "2024-W36",
    "2024-W37",
    "2024-W38",
    "2024-W39",
    "2024-W40",
    "2024-W41",
    "2024-W42",
    "2024-W43",
    "2024-W44",
    "2024-W45",
    "2024-W46",
    "2024-W47",
    "2024-W48",
    "2024-W49",
    "2024-W50",
    "2024-W51",
    "2024-W52",
    "2025-W01",
    "2025-W02",
    "2025-W03",
    "2025-W04",
    "2025-W05",
    "2025-W06",
    "2025-W07",
    "2025-W08",
    "2025-W09",
    "2025-W10",
    "2025-W11",
    "2025-W12",
    "2025-W13",
    "2025-W14",
    "2025-W15",
    "2025-W16",
    "2025-W17",
    "2025-W18",
    "2025-W19",
    "2025-W20",
    "2025-W21",
    "2025-W22",
    "2025-W23",
    "2025-W24",
    "2025-W25",
    "2025-W26",
    "2025-W27",
    "2025-W28",
    "2025-W29",
    "2025-W30",
    "2025-W31",
    "2025-W32",
    "2025-W33",
    "2025-W34",
    "2025-W35",
    "2025-W36",
    "2025-W37",
    "2025-W38",
    "2025-W39",
    "2025-W40",
    "2025-W41",
    "2025-W42",
    "2025-W43",
    "2025-W44",
    "2025-W45",
    "2025-W46",
    "2025-W47",
    "2025-W48",
    "2025-W49",
    "2025-W50",
    "2025-W51",
    "2025-W52",
    "2026-W01",
    "2026-W02",
    "2026-W03",
    "2026-W04",
    "2026-W05",
    "2026-W06",
    "2026-W07",
    "2026-W09",
    "2026-W10",
    "2026-W11",
    "2026-W12",
    "2026-W13",
    "2026-W14",
    "2026-W15",
    "2026-W16",
    "2026-W17",
    "2026-W18",
    "2026-W19",
    "2026-W20",
    "2026-W21",
    "2026-W22",
    "2026-W23",
    "2026-W24",
    "2026-W25",
    "2026-W26"
  ],
  "repos": [
    {
      "name": "ge",
      "path": "cann/ge",
      "total": 3648,
      "data": [
        0,
        0,
        0,
        0,
        0,
        0,
        0,
        0,
        0,
        0,
        0,
        0,
        0,
        0,
        0,
        0,
        0,
        0,
        0,
        0,
        0,
        0,
        0,
        0,
        0,
        0,
        0,
        0,
        0,
        0,
        0,
        0,
        0,
        0,
        0,
        0,
        0,
        0,
        0,
        0,
        0,
        0,
        0,
        0,
        0,
        0,
        0,
        0,
        0,
        0,
        0,
        0,
        0,
        0,
        0,
        0,
        0,
        0,
        0,
        0,
        0,
        0,
        0,
        0,
        0,
        0,
        0,
        0,
        0,
        0,
        0,
        0,
        0,
        0,
        0,
        0,
        0,
        0,
        0,
        0,
        0,
        0,
        0,
        0,
        0,
        0,
        0,
        0,
        0,
        0,
        0,
        0,
        0,
        0,
        0,
        0,
        0,
        0,
        0,
        0,
        0,
        0,
        0,
        0,
        0,
        0,
        0,
        0,
        0,
        0,
        0,
        0,
        0,
        0,
        0,
        0,
        0,
        0,
        0,
        0,
        0,
        0,
        0,
        0,
        0,
        0,
        0,
        0,
        16,
        43,
        42,
        63,
        44,
        120,
        177,
        134,
        150,
        168,
        218,
        204,
        229,
        141,
        89,
        206,
        277,
        199,
        179,
        233,
        184,
        147,
        146,
        110,
        92,
        37
      ]
    },
    {
      "name": "torchair",
      "path": "Ascend/torchair",
      "total": 3238,
      "data": [
        1,
        8,
        8,
        13,
        9,
        13,
        14,
        17,
        9,
        6,
        6,
        15,
        7,
        8,
        10,
        13,
        16,
        5,
        15,
        16,
        17,
        16,
        18,
        18,
        23,
        11,
        50,
        24,
        41,
        31,
        10,
        5,
        33,
        21,
        26,
        28,
        59,
        48,
        22,
        28,
        26,
        18,
        7,
        21,
        9,
        22,
        21,
        15,
        15,
        42,
        31,
        23,
        12,
        15,
        17,
        14,
        15,
        18,
        8,
        11,
        6,
        23,
        26,
        19,
        1,
        8,
        21,
        14,
        14,
        8,
        5,
        16,
        15,
        29,
        13,
        19,
        20,
        10,
        9,
        8,
        4,
        2,
        15,
        7,
        20,
        9,
        12,
        17,
        18,
        20,
        27,
        27,
        32,
        23,
        19,
        15,
        22,
        26,
        20,
        14,
        15,
        33,
        34,
        15,
        20,
        16,
        14,
        22,
        16,
        18,
        17,
        15,
        11,
        7,
        18,
        23,
        7,
        5,
        18,
        32,
        37,
        30,
        30,
        35,
        65,
        30,
        32,
        43,
        26,
        29,
        34,
        41,
        25,
        34,
        27,
        26,
        32,
        28,
        44,
        36,
        39,
        43,
        27,
        42,
        66,
        16,
        21,
        31,
        25,
        49,
        33,
        43,
        26,
        6
      ]
    },
    {
      "name": "graph-autofusion",
      "path": "cann/graph-autofusion",
      "total": 988,
      "data": [
        0,
        0,
        0,
        0,
        0,
        0,
        0,
        0,
        0,
        0,
        0,
        0,
        0,
        0,
        0,
        0,
        0,
        0,
        0,
        0,
        0,
        0,
        0,
        0,
        0,
        0,
        0,
        0,
        0,
        0,
        0,
        0,
        0,
        0,
        0,
        0,
        0,
        0,
        0,
        0,
        0,
        0,
        0,
        0,
        0,
        0,
        0,
        0,
        0,
        0,
        0,
        0,
        0,
        0,
        0,
        0,
        0,
        0,
        0,
        0,
        0,
        0,
        0,
        0,
        0,
        0,
        0,
        0,
        0,
        0,
        0,
        0,
        0,
        0,
        0,
        0,
        0,
        0,
        0,
        0,
        0,
        0,
        0,
        0,
        0,
        0,
        0,
        0,
        0,
        0,
        0,
        0,
        0,
        0,
        0,
        0,
        0,
        0,
        0,
        0,
        0,
        0,
        0,
        0,
        0,
        0,
        0,
        0,
        0,
        0,
        0,
        0,
        0,
        0,
        0,
        0,
        0,
        0,
        0,
        0,
        3,
        9,
        2,
        1,
        7,
        3,
        5,
        4,
        9,
        2,
        5,
        0,
        2,
        4,
        3,
        3,
        26,
        22,
        25,
        30,
        42,
        26,
        19,
        25,
        23,
        31,
        26,
        28,
        67,
        133,
        132,
        129,
        123,
        19
      ]
    },
    {
      "name": "hixl",
      "path": "cann/hixl",
      "total": 661,
      "data": [
        0,
        0,
        0,
        0,
        0,
        0,
        0,
        0,
        0,
        0,
        0,
        0,
        0,
        0,
        0,
        0,
        0,
        0,
        0,
        0,
        0,
        0,
        0,
        0,
        0,
        0,
        0,
        0,
        0,
        0,
        0,
        0,
        0,
        0,
        0,
        0,
        0,
        0,
        0,
        0,
        0,
        0,
        0,
        0,
        0,
        0,
        0,
        0,
        0,
        0,
        0,
        0,
        0,
        0,
        0,
        0,
        0,
        0,
        0,
        0,
        0,
        0,
        0,
        0,
        0,
        0,
        0,
        0,
        0,
        0,
        0,
        0,
        0,
        0,
        0,
        0,
        0,
        0,
        0,
        0,
        0,
        0,
        0,
        0,
        0,
        0,
        0,
        0,
        0,
        0,
        0,
        0,
        0,
        0,
        0,
        0,
        0,
        0,
        0,
        0,
        0,
        0,
        0,
        0,
        0,
        0,
        0,
        0,
        0,
        0,
        0,
        0,
        0,
        0,
        0,
        0,
        0,
        0,
        2,
        6,
        6,
        15,
        8,
        13,
        21,
        12,
        6,
        8,
        15,
        6,
        17,
        8,
        3,
        14,
        15,
        39,
        12,
        16,
        30,
        26,
        37,
        18,
        18,
        22,
        22,
        18,
        14,
        28,
        49,
        28,
        43,
        27,
        34,
        5
      ]
    },
    {
      "name": "torchtitan-npu",
      "path": "cann/torchtitan-npu",
      "total": 367,
      "data": [
        0,
        0,
        0,
        0,
        0,
        0,
        0,
        0,
        0,
        0,
        0,
        0,
        0,
        0,
        0,
        0,
        0,
        0,
        0,
        0,
        0,
        0,
        0,
        0,
        0,
        0,
        0,
        0,
        0,
        0,
        0,
        0,
        0,
        0,
        0,
        0,
        0,
        0,
        0,
        0,
        0,
        0,
        0,
        0,
        0,
        0,
        0,
        0,
        0,
        0,
        0,
        0,
        0,
        0,
        0,
        0,
        0,
        0,
        0,
        0,
        0,
        0,
        0,
        0,
        0,
        0,
        0,
        0,
        0,
        0,
        0,
        0,
        0,
        0,
        0,
        0,
        0,
        0,
        0,
        0,
        0,
        0,
        0,
        0,
        0,
        0,
        0,
        0,
        0,
        0,
        0,
        0,
        0,
        0,
        0,
        0,
        0,
        0,
        0,
        0,
        0,
        0,
        0,
        0,
        0,
        0,
        0,
        0,
        0,
        0,
        0,
        0,
        0,
        0,
        0,
        0,
        0,
        0,
        0,
        0,
        0,
        0,
        0,
        0,
        0,
        0,
        0,
        0,
        0,
        0,
        0,
        0,
        3,
        22,
        2,
        7,
        14,
        8,
        7,
        14,
        16,
        15,
        17,
        14,
        14,
        14,
        15,
        20,
        40,
        43,
        27,
        41,
        12,
        2
      ]
    }
  ],
  "generated_at": "2026-06-22"
}